wikiparser/__init__.py
wikiparser/wikiparser.py
wikiparser-1.0.1.dist-info/DESCRIPTION.rst
wikiparser-1.0.1.dist-info/METADATA
wikiparser-1.0.1.dist-info/RECORD
wikiparser-1.0.1.dist-info/WHEEL
wikiparser-1.0.1.dist-info/entry_points.txt
wikiparser-1.0.1.dist-info/metadata.json
wikiparser-1.0.1.dist-info/top_level.txt
