Metadata-Version: 2.0
Name: wikiparser
Version: 1.0.1
Summary: Wikipedia parser
Home-page: https://github.com/KiranNiranjan/wiki-parser-py
Author: Kiran Niranjan (KiKe)
Author-email: kiranleo1992@gmail.com
License: MIT
Keywords: wiki parser html to json wikipedia
Platform: UNKNOWN
Classifier: Development Status :: 3 - Alpha
Classifier: Intended Audience :: Developers
Classifier: Topic :: Software Development :: Build Tools
Classifier: License :: OSI Approved :: MIT License
Classifier: Programming Language :: Python :: 3.6
Requires-Dist: bs4
Requires-Dist: requests
Provides-Extra: dev
Requires-Dist: check-manifest; extra == 'dev'
Provides-Extra: test
Requires-Dist: coverage; extra == 'test'
